pysoda/__init__.py
pysoda/constants.py
pysoda/core/__init__.py
pysoda/core/dataset_generation/__init__.py
pysoda/core/dataset_generation/manifestSession/__init__.py
pysoda/core/dataset_generation/manifestSession/manifest_session.py
pysoda/core/dataset_generation/upload.py
pysoda/core/dataset_importing/__init__.py
pysoda/core/dataset_importing/import_dataset.py
pysoda/core/metadata/__init__.py
pysoda/core/metadata/code_description.py
pysoda/core/metadata/constants.py
pysoda/core/metadata/dataset_description.py
pysoda/core/metadata/excel_utils.py
pysoda/core/metadata/helpers.py
pysoda/core/metadata/manifest.py
pysoda/core/metadata/manifest_package/__init__.py
pysoda/core/metadata/manifest_package/manifest.py
pysoda/core/metadata/manifest_package/manifest_import.py
pysoda/core/metadata/manifest_package/manifest_writer.py
pysoda/core/metadata/performances.py
pysoda/core/metadata/resources.py
pysoda/core/metadata/samples.py
pysoda/core/metadata/sites.py
pysoda/core/metadata/subjects.py
pysoda/core/metadata/submission.py
pysoda/core/metadata/text_metadata.py
pysoda/core/metadata_templates/CHANGES
pysoda/core/metadata_templates/LICENSE
pysoda/core/metadata_templates/README.md
pysoda/core/metadata_templates/__init__.py
pysoda/core/metadata_templates/code_description.xlsx
pysoda/core/metadata_templates/code_parameters.xlsx
pysoda/core/metadata_templates/dataset_description.xlsx
pysoda/core/metadata_templates/manifest.xlsx
pysoda/core/metadata_templates/performances.xlsx
pysoda/core/metadata_templates/resources.xlsx
pysoda/core/metadata_templates/samples.xlsx
pysoda/core/metadata_templates/sites.xlsx
pysoda/core/metadata_templates/subjects.xlsx
pysoda/core/metadata_templates/subjects_pools_samples_structure.xlsx
pysoda/core/metadata_templates/subjects_pools_samples_structure_example.xlsx
pysoda/core/metadata_templates/submission.xlsx
pysoda/core/permissions/__init__.py
pysoda/core/permissions/permissions.py
pysoda/core/pysoda/__init__.py
pysoda/core/pysoda/soda.py
pysoda_fairdataihub_tools-0.1.61.dist-info/LICENSE
pysoda_fairdataihub_tools-0.1.61.dist-info/METADATA
pysoda_fairdataihub_tools-0.1.61.dist-info/WHEEL
pysoda_fairdataihub_tools-0.1.61.dist-info/RECORD
