Metadata-Version: 2.3
Name: pysoda-fairdataihub-tools
Version: 0.1.61
Summary: Pysoda package for Fairdataihub tools
License: MIT
Author: Your Name
Author-email: cmarroquin@calmi2.org
Requires-Python: >=3.6
Classifier: License :: OSI Approved :: MIT License
Classifier: Programming Language :: Python :: 3
Classifier: Programming Language :: Python :: 3.6
Classifier: Programming Language :: Python :: 3.7
Classifier: Programming Language :: Python :: 3.8
Classifier: Programming Language :: Python :: 3.9
Classifier: Programming Language :: Python :: 3.10
Classifier: Programming Language :: Python :: 3.11
Classifier: Programming Language :: Python :: 3.12
Classifier: Programming Language :: Python :: 3.13
Requires-Dist: openpyxl
Project-URL: Homepage, https://github.com/fairdataihub/pysoda
Project-URL: Repository, https://github.com/fairdataihub/pysoda
